tizero/__init__.py
tizero/cli/__init__.py
tizero/cli/cli.py
tizero/cli/dump2video.py
tizero/cli/evaluation.py
tizero/cli/show_dump.py
tizero/cli/show_keypoint.py
tizero/football_env/__init__.py
tizero/football_env/football_jidi_eval.py
tizero/football_env/football_pettingzoo.py
tizero/football_env/core/__init__.py
tizero/football_env/core/config.py
tizero/football_env/core/football_env.py
tizero/football_env/core/football_env_core.py
tizero/football_env/core/scenario_builder.py
tizero/football_env/scenarios/11_vs_11_determ_False.py
tizero/football_env/scenarios/11_vs_11_determ_True.py
tizero/football_env/scenarios/11_vs_11_jidi.py
tizero/football_env/scenarios/11_vs_11_jidi_diff.py
tizero/football_env/scenarios/11_vs_11_jidi_eval.py
tizero/football_env/scenarios/11_vs_11_jidi_new.py
tizero/football_env/scenarios/11_vs_11_jidi_reverse.py
tizero/football_env/scenarios/11_vs_11_jidi_v2.py
tizero/football_env/scenarios/11_vs_11_kaggle.py
tizero/football_env/scenarios/11_vs_11_stochastic.py
tizero/football_env/scenarios/__init__.py
tizero/football_env/scenarios/academy_3_vs_1_with_keeper.py
tizero/football_env/scenarios/academy_corner.py
tizero/football_env/scenarios/academy_counterattack_easy.py
tizero/football_env/scenarios/academy_counterattack_hard.py
tizero/football_env/scenarios/academy_empty_goal.py
tizero/football_env/scenarios/academy_empty_goal_close.py
tizero/football_env/scenarios/academy_pass_and_shoot_with_keeper.py
tizero/football_env/scenarios/academy_run_pass_and_shoot_with_keeper.py
tizero/football_env/scenarios/academy_run_to_score.py
tizero/football_env/scenarios/academy_run_to_score_with_keeper.py
tizero/football_env/scenarios/debug_football.py
tizero/football_env/scenarios/football_scenario.py
tizero/football_env/scenarios/position_test.py
tizero/utils/__init__.py
tizero/utils/script_helpers.py
tizero/utils/util.py
tizero/utils/visualize_tools/__init__.py
tizero/utils/visualize_tools/game_graph/__init__.py
tizero-0.0.3.dist-info/LICENSE
tizero-0.0.3.dist-info/METADATA
tizero-0.0.3.dist-info/WHEEL
tizero-0.0.3.dist-info/entry_points.txt
tizero-0.0.3.dist-info/top_level.txt
tizero-0.0.3.dist-info/RECORD
