Metadata-Version: 2.1
Name: tizero
Version: 0.0.3
Summary: Toolkit and agents for Google Research Football
Home-page: https://github.com/OpenRL-Lab/TiZero
Author: openrl contributors
Author-email: huangsy1314@163.com
Project-URL: Code, https://github.com/OpenRL-Lab/TiZero
Project-URL: Documentation, https://tizero.readthedocs.io/
Keywords: reinforcement-learning multi-agent google research football
Classifier: Development Status :: 5 - Production/Stable
Classifier: Intended Audience :: Science/Research
Classifier: Topic :: Scientific/Engineering :: Artificial Intelligence
Classifier: Topic :: Software Development :: Libraries :: Python Modules
Classifier: Programming Language :: Python :: 3.8
Classifier: Programming Language :: Python :: 3.9
Classifier: Programming Language :: Python :: 3.10
Classifier: Programming Language :: Python :: 3.11
Classifier: License :: OSI Approved :: Apache Software License
Classifier: Operating System :: OS Independent
Requires-Python: >=3.8
License-File: LICENSE
Requires-Dist: setuptools >=67.0
Requires-Dist: psutil
Requires-Dist: wheel
Requires-Dist: click
Requires-Dist: termcolor
Requires-Dist: tabulate
Requires-Dist: lz4
Requires-Dist: six
Requires-Dist: tqdm
Requires-Dist: openrl
Provides-Extra: dev
Requires-Dist: build ; extra == 'dev'
Requires-Dist: twine ; extra == 'dev'
Provides-Extra: test
Requires-Dist: pytest ; extra == 'test'
Requires-Dist: pytest-cov ; extra == 'test'
Requires-Dist: mypy ; extra == 'test'
Requires-Dist: isort ; extra == 'test'
Requires-Dist: black ; extra == 'test'
Requires-Dist: ruff ; extra == 'test'
Requires-Dist: gpustat ; extra == 'test'
